{
  "?xml": "",
  "rss": {
    "channel": {
      "atom:link": "",
      "title": "The author, Séamas O'Reilly / @shockproofbeats",
      "link": "http://nitter.42l.fr/shockproofbeats",
      "description": "Twitter feed for: @shockproofbeats. Generated by nitter.42l.fr",
      "language": "en-us",
      "ttl": 40,
      "image": {
        "title": "The author, Séamas O'Reilly / @shockproofbeats",
        "link": "http://nitter.42l.fr/shockproofbeats",
        "url": "http://nitter.42l.fr/pic/pbs.twimg.com%2Fprofile_images%2F1282765412539695104%2F4Z-HDQsh_400x400.jpg",
        "width": 128,
        "height": 128
      },
      "item": [
        {
          "title": "RT by @shockproofbeats: Occasionally I am reminded of my all time favourite piece of internet: this Reddit post from 6 years ago in which a guy claims he ruined dinner with his girlfriend's parents, after he refused to stop saying he didn't know what a potato was.",
          "dc:creator": "@shockproofbeats",
          "description": "<p>Occasionally I am reminded of my all time favourite piece of internet: this Reddit post from 6 years ago in which a guy claims he ruined dinner with his girlfriend's parents, after he refused to stop saying he didn't know what a potato was.</p>\n<img src=\"http://nitter.42l.fr/pic/media%2FE5I6kekWQAMGh18.jpg\" style=\"max-width:250px;\" />\n<img src=\"http://nitter.42l.fr/pic/media%2FE5I6qVXXwAg1gG6.png\" style=\"max-width:250px;\" />\n<img src=\"http://nitter.42l.fr/pic/media%2FE5I6vjYXIAEOJcB.png\" style=\"max-width:250px;\" />",
          "pubDate": "Wed, 30 Jun 2021 15:13:09 GMT",
          "guid": "http://nitter.42l.fr/shockproofbeats/status/1410255089537798144#m",
          "link": "http://nitter.42l.fr/shockproofbeats/status/1410255089537798144#m"
        },
        {
          "title": "R to @shockproofbeats: At one point, his character injects his \"heart\" with adrenaline, but it's clear that the injection site is in his stomach. Cage claims this - and his decision to sit cross legged for the scene - was a conscious private choice, intended to invoke the imagery of seppuku.",
          "dc:creator": "@shockproofbeats",
          "description": "<p>At one point, his character injects his \"heart\" with adrenaline, but it's clear that the injection site is in his stomach. Cage claims this - and his decision to sit cross legged for the scene - was a conscious private choice, intended to invoke the imagery of seppuku.</p>",
          "pubDate": "Wed, 29 Jun 2022 23:39:42 GMT",
          "guid": "http://nitter.42l.fr/shockproofbeats/status/1542291749569269760#m",
          "link": "http://nitter.42l.fr/shockproofbeats/status/1542291749569269760#m"
        },
        {
          "title": "R to @kibblesmith: Special commendation to Nicholas Cage on The Rock commentary, who stressed that his performance was, to a baffling extent, based on his love of kabuki theatre.",
          "dc:creator": "@shockproofbeats",
          "description": "<p>Special commendation to Nicholas Cage on The Rock commentary, who stressed that his performance was, to a baffling extent, based on his love of kabuki theatre.</p>",
          "pubDate": "Wed, 29 Jun 2022 23:24:11 GMT",
          "guid": "http://nitter.42l.fr/shockproofbeats/status/1542287846177914880#m",
          "link": "http://nitter.42l.fr/shockproofbeats/status/1542287846177914880#m"
        },
        {
          "title": "In the grand realm of overthinking comedy nerds, Joel is a cruel, strutting king - I've just backed this and suggest you do the same.",
          "dc:creator": "@shockproofbeats",
          "description": "<p>In the grand realm of overthinking comedy nerds, Joel is a cruel, strutting king - I've just backed this and suggest you do the same.</p>\n<p><a href=\"http://nitter.42l.fr/unbounders/status/1542069983945048064#m\">nitter.42l.fr/unbounders/status/1542069983945048064#m</a></p>",
          "pubDate": "Wed, 29 Jun 2022 16:03:23 GMT",
          "guid": "http://nitter.42l.fr/shockproofbeats/status/1542176916077252617#m",
          "link": "http://nitter.42l.fr/shockproofbeats/status/1542176916077252617#m"
        },
        {
          "title": "R to @gralefrit: This looks extremely great!",
          "dc:creator": "@shockproofbeats",
          "description": "<p>This looks extremely great!</p>",
          "pubDate": "Wed, 29 Jun 2022 15:56:03 GMT",
          "guid": "http://nitter.42l.fr/shockproofbeats/status/1542175071212560384#m",
          "link": "http://nitter.42l.fr/shockproofbeats/status/1542175071212560384#m"
        },
        {
          "title": "R to @shockproofbeats: how do i tell all the people arguing about voltage in my replies that this was 99% an excuse to write a headline in the New York Times' clause-mangling house style. \n\nFrom Handsome Writer's \"Kettle\" Tweet, Fresh Dilemmas Arise.",
          "dc:creator": "@shockproofbeats",
          "description": "<p>how do i tell all the people arguing about voltage in my replies that this was 99% an excuse to write a headline in the New York Times' clause-mangling house style. <br>\n<br>\nFrom Handsome Writer's \"Kettle\" Tweet, Fresh Dilemmas Arise.</p>",
          "pubDate": "Wed, 29 Jun 2022 14:24:43 GMT",
          "guid": "http://nitter.42l.fr/shockproofbeats/status/1542152086934241282#m",
          "link": "http://nitter.42l.fr/shockproofbeats/status/1542152086934241282#m"
        },
        {
          "title": "For Fans Of Heated Water, A Modern Technique Emerges",
          "dc:creator": "@shockproofbeats",
          "description": "<p>For Fans Of Heated Water, A Modern Technique Emerges</p>\n<p><a href=\"http://nitter.42l.fr/stefanroberts/status/1542077697542836225#m\">nitter.42l.fr/stefanroberts/status/1542077697542836225#m</a></p>",
          "pubDate": "Wed, 29 Jun 2022 11:52:31 GMT",
          "guid": "http://nitter.42l.fr/shockproofbeats/status/1542113782561996810#m",
          "link": "http://nitter.42l.fr/shockproofbeats/status/1542113782561996810#m"
        },
        {
          "title": "RT by @shockproofbeats: An absolute gem of a piece from the legendary @benschott",
          "dc:creator": "@The_Fence_Mag",
          "description": "<p>An absolute gem of a piece from the legendary <a href=\"http://nitter.42l.fr/benschott\" title=\"Ben Schott\">@benschott</a></p>\n<img src=\"http://nitter.42l.fr/pic/media%2FFWaq92EXEAI1-ry.jpg\" style=\"max-width:250px;\" />\n<img src=\"http://nitter.42l.fr/pic/media%2FFWaq92BXkAcnvP8.jpg\" style=\"max-width:250px;\" />\n<img src=\"http://nitter.42l.fr/pic/media%2FFWaq92BWIAAEc_l.jpg\" style=\"max-width:250px;\" />\n<img src=\"http://nitter.42l.fr/pic/media%2FFWaq92AXkAIIenZ.jpg\" style=\"max-width:250px;\" />",
          "pubDate": "Wed, 29 Jun 2022 11:29:10 GMT",
          "guid": "http://nitter.42l.fr/The_Fence_Mag/status/1542107906375618561#m",
          "link": "http://nitter.42l.fr/The_Fence_Mag/status/1542107906375618561#m"
        },
        {
          "title": "Savile exonerated 14 murder victims, 7 of whom were children. Blaming it, and not the Government, for not \"achieving reconciliation\" is pretty repugnant, considering the Tories made *refusing to prosecute anyone based on its findings* a fucking campaign pledge.",
          "dc:creator": "@shockproofbeats",
          "description": "<p>Savile exonerated 14 murder victims, 7 of whom were children. Blaming it, and not the Government, for not \"achieving reconciliation\" is pretty repugnant, considering the Tories made *refusing to prosecute anyone based on its findings* a fucking campaign pledge.</p>\n<p><a href=\"http://nitter.42l.fr/brokenbottleboy/status/1542036465672224769#m\">nitter.42l.fr/brokenbottleboy/status/1542036465672224769#m</a></p>",
          "pubDate": "Wed, 29 Jun 2022 10:14:00 GMT",
          "guid": "http://nitter.42l.fr/shockproofbeats/status/1542088990496636928#m",
          "link": "http://nitter.42l.fr/shockproofbeats/status/1542088990496636928#m"
        },
        {
          "title": "R to @housetoastonish: We deserved 1 (one) nice thing this week/month/year",
          "dc:creator": "@shockproofbeats",
          "description": "<p>We deserved 1 (one) nice thing this week/month/year</p>",
          "pubDate": "Tue, 28 Jun 2022 20:13:16 GMT",
          "guid": "http://nitter.42l.fr/shockproofbeats/status/1541877411884810242#m",
          "link": "http://nitter.42l.fr/shockproofbeats/status/1541877411884810242#m"
        },
        {
          "title": "R to @housetoastonish: I'm vibrating",
          "dc:creator": "@shockproofbeats",
          "description": "<p>I'm vibrating</p>",
          "pubDate": "Tue, 28 Jun 2022 20:11:46 GMT",
          "guid": "http://nitter.42l.fr/shockproofbeats/status/1541877034988847105#m",
          "link": "http://nitter.42l.fr/shockproofbeats/status/1541877034988847105#m"
        },
        {
          "title": "!!!!!!!!!!!!!!!!",
          "dc:creator": "@shockproofbeats",
          "description": "<p>!!!!!!!!!!!!!!!!</p>\n<p><a href=\"http://nitter.42l.fr/SkilletDoux/status/1541800101428879361#m\">nitter.42l.fr/SkilletDoux/status/1541800101428879361#m</a></p>",
          "pubDate": "Tue, 28 Jun 2022 20:11:20 GMT",
          "guid": "http://nitter.42l.fr/shockproofbeats/status/1541876926415097856#m",
          "link": "http://nitter.42l.fr/shockproofbeats/status/1541876926415097856#m"
        },
        {
          "title": "RT by @shockproofbeats: Gypsies & Travellers existence is illegal as of today. There’s too much I can say, but honestly, I’d just end up upsetting too many.",
          "dc:creator": "@thatbloodyMikey",
          "description": "<p>Gypsies & Travellers existence is illegal as of today. There’s too much I can say, but honestly, I’d just end up upsetting too many.</p>",
          "pubDate": "Tue, 28 Jun 2022 11:22:57 GMT",
          "guid": "http://nitter.42l.fr/thatbloodyMikey/status/1541743952533094400#m",
          "link": "http://nitter.42l.fr/thatbloodyMikey/status/1541743952533094400#m"
        },
        {
          "title": "RT by @shockproofbeats: There are people on the Conservative grift circuit who imho are just saying what they think the punters want, your Grimeses and your Foxes, but Montie is the truest of true believers. He is a man to be feared, not to be mocked.",
          "dc:creator": "@Dara_bhur_gCara",
          "description": "<p>There are people on the Conservative grift circuit who imho are just saying what they think the punters want, your Grimeses and your Foxes, but Montie is the truest of true believers. He is a man to be feared, not to be mocked.</p>\n<img src=\"http://nitter.42l.fr/pic/media%2FFWWaqAxXkAEP_KY.jpg\" style=\"max-width:250px;\" />",
          "pubDate": "Tue, 28 Jun 2022 15:39:29 GMT",
          "guid": "http://nitter.42l.fr/Dara_bhur_gCara/status/1541808511276941312#m",
          "link": "http://nitter.42l.fr/Dara_bhur_gCara/status/1541808511276941312#m"
        },
        {
          "title": "RT by @shockproofbeats: Nobody is complaining ( as Starmer implies) that he has changed his mind since he was a teenager. The issue is that he has dropped every single one of the 10 pledges he made in 2020 to get elected leader.",
          "dc:creator": "@HackneyAbbott",
          "description": "<p>Nobody is complaining ( as Starmer implies) that he has changed his mind since he was a teenager. The issue is that he has dropped every single one of the 10 pledges he made in 2020 to get elected leader.</p>",
          "pubDate": "Tue, 28 Jun 2022 14:04:36 GMT",
          "guid": "http://nitter.42l.fr/HackneyAbbott/status/1541784634777903106#m",
          "link": "http://nitter.42l.fr/HackneyAbbott/status/1541784634777903106#m"
        },
        {
          "title": "RT by @shockproofbeats: From today GRT in the UK are criminalised as a nomadic people due to the Policing Act. Irish Travellers are criminalised in Ireland since 2002. Solidarity in our journey for equality.",
          "dc:creator": "@Minceirbeoir",
          "description": "<p>From today GRT in the UK are criminalised as a nomadic people due to the Policing Act. Irish Travellers are criminalised in Ireland since 2002. Solidarity in our journey for equality.</p>",
          "pubDate": "Tue, 28 Jun 2022 12:03:25 GMT",
          "guid": "http://nitter.42l.fr/Minceirbeoir/status/1541754137037230084#m",
          "link": "http://nitter.42l.fr/Minceirbeoir/status/1541754137037230084#m"
        },
        {
          "title": "RT by @shockproofbeats: Devoted the last 15 years of my life to reading literature so i could help bring you this. \n\nKudos to @CharlieFBBaker1 @shockproofbeats @_F_B_G_ @alexschristian @kf_morris for writing all the jokes but still allowing me to take all the money – incredibly generous lads one and all",
          "dc:creator": "@John__Phipps",
          "description": "<p>Devoted the last 15 years of my life to reading literature so i could help bring you this. <br>\n<br>\nKudos to <a href=\"http://nitter.42l.fr/CharlieFBBaker1\" title=\"Charlie F B Baker\">@CharlieFBBaker1</a> <a href=\"http://nitter.42l.fr/shockproofbeats\" title=\"The author, Séamas O'Reilly\">@shockproofbeats</a> <a href=\"http://nitter.42l.fr/_F_B_G_\" title=\"Fergus Butler-Gallie\">@_F_B_G_</a> <a href=\"http://nitter.42l.fr/alexschristian\" title=\"Alex Christian\">@alexschristian</a> <a href=\"http://nitter.42l.fr/kf_morris\" title=\"Kieran Morris\">@kf_morris</a> for writing all the jokes but still allowing me to take all the money – incredibly generous lads one and all</p>\n<p><a href=\"http://nitter.42l.fr/The_Fence_Mag/status/1541747559747801088#m\">nitter.42l.fr/The_Fence_Mag/status/1541747559747801088#m</a></p>",
          "pubDate": "Tue, 28 Jun 2022 12:06:36 GMT",
          "guid": "http://nitter.42l.fr/John__Phipps/status/1541754938207965184#m",
          "link": "http://nitter.42l.fr/John__Phipps/status/1541754938207965184#m"
        },
        {
          "title": "RT by @shockproofbeats: We’ve got a book coming out!!!\n\nLiterary hilarities from the whole Fence team! Illustrations by me!\n\nI’m ridiculously excited!!!",
          "dc:creator": "@alexschristian",
          "description": "<p>We’ve got a book coming out!!!<br>\n<br>\nLiterary hilarities from the whole Fence team! Illustrations by me!<br>\n<br>\nI’m ridiculously excited!!!</p>\n<p><a href=\"http://nitter.42l.fr/The_Fence_Mag/status/1541747559747801088#m\">nitter.42l.fr/The_Fence_Mag/status/1541747559747801088#m</a></p>",
          "pubDate": "Tue, 28 Jun 2022 11:50:59 GMT",
          "guid": "http://nitter.42l.fr/alexschristian/status/1541751007339634689#m",
          "link": "http://nitter.42l.fr/alexschristian/status/1541751007339634689#m"
        },
        {
          "title": "R to @morris_kate: Kate! How lovely to hear, I'm so glad you enjoyed it and that I made a fool of you in public all the same. Thank you!",
          "dc:creator": "@shockproofbeats",
          "description": "<p>Kate! How lovely to hear, I'm so glad you enjoyed it and that I made a fool of you in public all the same. Thank you!</p>",
          "pubDate": "Tue, 28 Jun 2022 12:01:31 GMT",
          "guid": "http://nitter.42l.fr/shockproofbeats/status/1541753658290966530#m",
          "link": "http://nitter.42l.fr/shockproofbeats/status/1541753658290966530#m"
        },
        {
          "title": "R to @IanMartin: Thank you, Ian!",
          "dc:creator": "@shockproofbeats",
          "description": "<p>Thank you, Ian!</p>",
          "pubDate": "Tue, 28 Jun 2022 11:54:48 GMT",
          "guid": "http://nitter.42l.fr/shockproofbeats/status/1541751968577748996#m",
          "link": "http://nitter.42l.fr/shockproofbeats/status/1541751968577748996#m"
        }
      ]
    }
  }
}